pysmartlogger-1.3.0.dist-info/licenses/LICENSE
smartlogger/__init__.py
smartlogger/auto.py
smartlogger/config/__init__.py
smartlogger/config/colors.py
smartlogger/config/defaults.py
smartlogger/core/__init__.py
smartlogger/core/formatter.py
smartlogger/core/handler.py
smartlogger/core/monkey_patch.py
smartlogger/utils/__init__.py
smartlogger/utils/compatibility.py
smartlogger/utils/terminal.py
pysmartlogger-1.3.0.dist-info/METADATA
pysmartlogger-1.3.0.dist-info/WHEEL
pysmartlogger-1.3.0.dist-info/top_level.txt
pysmartlogger-1.3.0.dist-info/RECORD
