Metadata-Version: 2.4
Name: pysmartlogger
Version: 1.3.0
Summary: A cross-platform Python library that adds colorful logging capabilities to the standard logging module
Home-page: https://github.com/DeepPythonist/smartlogger
Author: Mohammad Rasol Esfandiari
Author-email: Mohammad Rasol Esfandiari <mrasolesfandiari@gmail.com>
Maintainer-email: Mohammad Rasol Esfandiari <mrasolesfandiari@gmail.com>
License: MIT
Project-URL: Homepage, https://github.com/DeepPythonist/smartlogger
Project-URL: Repository, https://github.com/DeepPythonist/smartlogger
Project-URL: Issues, https://github.com/DeepPythonist/smartlogger/issues
Project-URL: Changelog, https://github.com/DeepPythonist/smartlogger/blob/master/CHANGELOG.md
Keywords: logging,colors,terminal,cross-platform,python
Classifier: Development Status :: 5 - Production/Stable
Classifier: Intended Audience :: Developers
Classifier: License :: OSI Approved :: MIT License
Classifier: Operating System :: OS Independent
Classifier: Programming Language :: Python :: 3
Classifier: Programming Language :: Python :: 3.8
Classifier: Programming Language :: Python :: 3.9
Classifier: Programming Language :: Python :: 3.10
Classifier: Programming Language :: Python :: 3.11
Classifier: Programming Language :: Python :: 3.12
Classifier: Topic :: Software Development :: Libraries :: Python Modules
Classifier: Topic :: System :: Logging
Classifier: Topic :: Terminals
Classifier: Environment :: Console
Requires-Python: >=3.8
License-File: LICENSE
Dynamic: author
Dynamic: home-page
Dynamic: license-file
Dynamic: requires-python
